pixi_ros/__init__.py
pixi_ros/cli.py
pixi_ros/config.py
pixi_ros/init.py
pixi_ros/mappings.py
pixi_ros/package_xml.py
pixi_ros/utils.py
pixi_ros/workspace.py
pixi_ros/data/README.md
pixi_ros/data/README_PIXI.md.template
pixi_ros/data/conda-forge.yaml
pixi_ros-0.3.0.dist-info/METADATA
pixi_ros-0.3.0.dist-info/WHEEL
pixi_ros-0.3.0.dist-info/entry_points.txt
pixi_ros-0.3.0.dist-info/licenses/LICENSE
pixi_ros-0.3.0.dist-info/RECORD
