Metadata-Version: 2.4
Name: pixi-ros
Version: 0.3.0
Summary: Pixi extension for ROS package management
Project-URL: Homepage, https://github.com/ruben-arts/pixi-ros
Project-URL: Repository, https://github.com/ruben-arts/pixi-ros
Author-email: Ruben Arts <ruben@prefix.dev>
License-Expression: MIT
License-File: LICENSE
Requires-Python: >=3.10
Requires-Dist: lxml>=5.0.0
Requires-Dist: pathspec>=0.11.0
Requires-Dist: py-rattler>=0.6.0
Requires-Dist: pyyaml>=6.0
Requires-Dist: rich>=13.0.0
Requires-Dist: tomlkit>=0.12.0
Requires-Dist: typer>=0.12.0
